{
  "version": 1,
  "saved_at": "2026-05-15T19:17:16",
  "requested_title": "Rufous-vented Chachalaca",
  "resolved_title": "Rufous-vented chachalaca",
  "title_aliases": [
    "Rufous-vented Chachalaca"
  ],
  "bird_id": "bird-棕臀稚冠雉-4a4b1323",
  "raw_file": "bird-棕臀稚冠雉-4a4b1323.json",
  "bird": {
    "id": "bird-棕臀稚冠雉-4a4b1323",
    "name": "棕臀稚冠雉",
    "english_name": "Rufous-vented chachalaca",
    "latin_name": "Ortalis ruficauda",
    "summary": "棕臀稚冠雉（學名Ortalis ruficauda），又名棕臀小冠雉，是一種鳳冠雉科鳥類。 特徵 棕臀稚冠雉分佈在哥倫比亞東北部、委內瑞拉北部及多巴哥，更是多巴哥的國鳥。它們也被引入到格瑞納丁群島（the Grenadines）的貝基亞島（Bequia）及聯合島（Union I…",
    "lat": "4",
    "lng": "-72",
    "image_url": "https://upload.wikimedia.org/wikipedia/commons/thumb/1/13/Rufous-vented_Chachalaca_-_Guacharaca_del_Norte_%28Ortalis_ruficauda%29_%288629080871%29.jpg/960px-Rufous-vented_Chachalaca_-_Guacharaca_del_Norte_%28Ortalis_ruficauda%29_%288629080871%29.jpg?utm_source=en.wikipedia.org&utm_campaign=api&utm_content=thumbnail"
  },
  "locations": [
    {
      "id": "loc-哥伦比亚-5037b987",
      "name": "哥伦比亚",
      "summary": "哥伦比亚共和国（西班牙語：República de Colombia），通稱哥倫比亞（西班牙語：Colombia），是一個位於南美洲西北部的国家，同時是拉丁美洲第四大國家，為南美洲國家聯盟的前成員國（2018年8月退出）。它的北部是加勒比…",
      "lat": "4",
      "lng": "-72"
    },
    {
      "id": "loc-委內瑞拉-ef40e96b",
      "name": "委內瑞拉",
      "summary": "委内瑞拉玻利瓦尔共和国（西班牙語：República Bolivariana de Venezuela），通稱委內瑞拉（西班牙語：Venezuela），是一個位於南美洲北部的國家。其面積為912,050平方公里，2025年人口估計為318…",
      "lat": "7",
      "lng": "-65"
    },
    {
      "id": "loc-千里達及托巴哥-d1db4577",
      "name": "千里達及托巴哥",
      "summary": "千里達及托巴哥共和國（英語：Republic of Trinidad and Tobago），通稱千里達及托巴哥（英語：Trinidad and Tobago），是一個位於中美洲加勒比海南部、緊鄰委內瑞拉外海的島國。全國由兩個主要大島——…",
      "lat": "10.6",
      "lng": "-61.1"
    }
  ],
  "relations": [
    {
      "subject_id": "bird-棕臀稚冠雉-4a4b1323",
      "subject": "棕臀稚冠雉",
      "predicate": "distributed_in",
      "object_id": "loc-哥伦比亚-5037b987",
      "object": "哥伦比亚",
      "subject_type": "Bird",
      "object_type": "Location",
      "evidence": "It inhabits northeast Colombia and northern Venezuela where it is called guacharaca, and the island of Tobago in Trinidad and Tobago where it is known as the cocrico and is one of the country's two national birds (being featured on the country's coat of arms)",
      "object_summary": ""
    },
    {
      "subject_id": "bird-棕臀稚冠雉-4a4b1323",
      "subject": "棕臀稚冠雉",
      "predicate": "distributed_in",
      "object_id": "loc-委內瑞拉-ef40e96b",
      "object": "委內瑞拉",
      "subject_type": "Bird",
      "object_type": "Location",
      "evidence": "It inhabits northeast Colombia and northern Venezuela where it is called guacharaca, and the island of Tobago in Trinidad and Tobago where it is known as the cocrico and is one of the country's two national birds (being featured on the country's coat of arms)",
      "object_summary": ""
    },
    {
      "subject_id": "bird-棕臀稚冠雉-4a4b1323",
      "subject": "棕臀稚冠雉",
      "predicate": "distributed_in",
      "object_id": "loc-千里達及托巴哥-d1db4577",
      "object": "千里達及托巴哥",
      "subject_type": "Bird",
      "object_type": "Location",
      "evidence": "It inhabits northeast Colombia and northern Venezuela where it is called guacharaca, and the island of Tobago in Trinidad and Tobago where it is known as the cocrico and is one of the country's two national birds (being featured on the country's coat of arms)",
      "object_summary": ""
    },
    {
      "subject_id": "bird-棕臀稚冠雉-4a4b1323",
      "subject": "棕臀稚冠雉",
      "predicate": "has_status",
      "object_id": "status-lc",
      "object": "LC",
      "subject_type": "Bird",
      "object_type": "Status",
      "evidence": "status = LC",
      "object_summary": "IUCN 无危。"
    }
  ]
}