{
  "version": 1,
  "saved_at": "2026-05-21T17:51:33",
  "requested_title": "Greater Vasa Parrot",
  "resolved_title": "Greater vasa parrot",
  "title_aliases": [
    "Greater Vasa Parrot"
  ],
  "bird_id": "bird-greater-vasa-parrot-0135e99b",
  "raw_file": "bird-greater-vasa-parrot-0135e99b.json",
  "bird": {
    "id": "bird-greater-vasa-parrot-0135e99b",
    "name": "Greater vasa parrot",
    "english_name": "Greater vasa parrot",
    "latin_name": "Coracopsis vasa",
    "summary": "The greater vasa parrot (Coracopsis vasa) is one of two species of vasa parrot, the other being the lesser vasa parrot (C. nigra).",
    "lat": "",
    "lng": "",
    "image_url": "https://upload.wikimedia.org/wikipedia/commons/thumb/2/2d/Coracopsis_vasa_-Madagascar-8.jpg/960px-Coracopsis_vasa_-Madagascar-8.jpg"
  },
  "locations": [],
  "relations": [
    {
      "subject_id": "bird-greater-vasa-parrot-0135e99b",
      "subject": "Greater vasa parrot",
      "predicate": "has_status",
      "object_id": "status-lc",
      "object": "LC",
      "subject_type": "Bird",
      "object_type": "Status",
      "evidence": "status = LC",
      "object_summary": "IUCN 无危。"
    }
  ]
}