{"meta": {"centerNodeId": "taxonomy-genus-doricha", "centerNodeType": "taxonomy", "generatedAt": "2026-05-26T12:19:52", "includedNodeCount": 3, "includedLinkCount": 2, "layoutMode": "precomputed-static"}, "center": {"id": "taxonomy-genus-doricha", "name": "Doricha", "type": "taxonomy"}, "nodes": [{"id": "taxonomy-species-doricha-eliza", "name": "墨西哥剪尾蜂鸟", "latinName": "Doricha eliza", "type": "taxonomy", "taxonomyLevel": "species", "summary": "墨西哥剪尾蜂鸟（Doricha eliza）是图谱中的分类级分类节点，当前关联1种鸟类，如墨西哥剪尾蜂鸟。", "expandable": true, "memberCount": 1, "x": -210.71, "y": 115.56, "z": 191.5}, {"id": "taxonomy-species-doricha-enicura", "name": "细剪尾蜂鸟", "latinName": "Doricha enicura", "type": "taxonomy", "taxonomyLevel": "species", "summary": "细剪尾蜂鸟（Doricha enicura）是图谱中的分类级分类节点，当前关联1种鸟类，如细剪尾蜂鸟。", "expandable": true, "memberCount": 1, "x": -172.49, "y": -55.23, "z": -730.19}, {"id": "taxonomy-genus-doricha", "name": "Doricha", "latinName": "Doricha", "type": "taxonomy", "taxonomyLevel": "genus", "summary": "Doricha（Doricha）是图谱中的分类级分类节点，当前关联2种鸟类，如细剪尾蜂鸟、墨西哥剪尾蜂鸟。", "expandable": true, "memberCount": 2, "x": 323.28, "y": 243.11, "z": -61.9}], "links": [{"key": "taxonomy-species-doricha-enicura__belongs_to_genus__taxonomy-genus-doricha", "source": "taxonomy-species-doricha-enicura", "target": "taxonomy-genus-doricha", "relation": "belongs_to_genus", "label": "属于属", "evidence": "依据 birds.csv 分类字段补充：细剪尾蜂鸟 属于属 Doricha。"}, {"key": "taxonomy-species-doricha-eliza__belongs_to_genus__taxonomy-genus-doricha", "source": "taxonomy-species-doricha-eliza", "target": "taxonomy-genus-doricha", "relation": "belongs_to_genus", "label": "属于属", "evidence": "依据 birds.csv 分类字段补充：墨西哥剪尾蜂鸟 属于属 Doricha。"}]}