{"meta": {"centerNodeId": "taxonomy-genus-arremon", "centerNodeType": "taxonomy", "generatedAt": "2026-05-27T17:26:07", "includedNodeCount": 23, "includedLinkCount": 22, "layoutMode": "precomputed-static"}, "center": {"id": "taxonomy-genus-arremon", "name": "Arremon", "type": "taxonomy"}, "nodes": [{"id": "taxonomy-species-arremon-aurantiirostris", "name": "Orange-billed sparrow", "latinName": "Arremon aurantiirostris", "type": "taxonomy", "taxonomyLevel": "species", "summary": "Orange-billed sparrow（Arremon aurantiirostris）是图谱中的分类级分类节点，当前关联1种鸟类，如Orange-billed sparrow。", "expandable": true, "memberCount": 1, "x": 5.02, "y": 56.71, "z": -372.21}, {"id": "taxonomy-species-arremon-assimilis", "name": "Grey-browed brushfinch", "latinName": "Arremon assimilis", "type": "taxonomy", "taxonomyLevel": "species", "summary": "Grey-browed brushfinch（Arremon assimilis）是图谱中的分类级分类节点，当前关联1种鸟类，如Grey-browed brushfinch。", "expandable": true, "memberCount": 1, "x": 307.68, "y": 528.01, "z": -210.52}, {"id": "taxonomy-species-arremon-crassirostris", "name": "Sooty-faced finch", "latinName": "Arremon crassirostris", "type": "taxonomy", "taxonomyLevel": "species", "summary": "Sooty-faced finch（Arremon crassirostris）是图谱中的分类级分类节点，当前关联1种鸟类，如Sooty-faced finch。", "expandable": true, "memberCount": 1, "x": -82.15, "y": 372.47, "z": -125.26}, {"id": "taxonomy-species-arremon-atricapillus", "name": "Black-headed brushfinch", "latinName": "Arremon atricapillus", "type": "taxonomy", "taxonomyLevel": "species", "summary": "Black-headed brushfinch（Arremon atricapillus）是图谱中的分类级分类节点，当前关联1种鸟类，如Black-headed brushfinch。", "expandable": true, "memberCount": 1, "x": 236.09, "y": -489.96, "z": 569.43}, {"id": "taxonomy-genus-arremon", "name": "Arremon", "latinName": "Arremon", "type": "taxonomy", "taxonomyLevel": "genus", "summary": "Arremon（Arremon）是图谱中的分类级分类节点，当前关联22种鸟类，如Costa Rican brushfinch、Sierra Nevada brushfinch、Perijá brushfinch等22种鸟类。", "expandable": true, "memberCount": 22, "x": -587.23, "y": -398.44, "z": -16.44}, {"id": "taxonomy-species-arremon-axillaris", "name": "Yellow-mandibled sparrow", "latinName": "Arremon axillaris", "type": "taxonomy", "taxonomyLevel": "species", "summary": "Yellow-mandibled sparrow（Arremon axillaris）是图谱中的分类级分类节点，当前关联1种鸟类，如Yellow-mandibled sparrow。", "expandable": true, "memberCount": 1, "x": 387.63, "y": -610.75, "z": -590.85}, {"id": "taxonomy-species-arremon-basilicus", "name": "Sierra Nevada brushfinch", "latinName": "Arremon basilicus", "type": "taxonomy", "taxonomyLevel": "species", "summary": "Sierra Nevada brushfinch（Arremon basilicus）是图谱中的分类级分类节点，当前关联1种鸟类，如Sierra Nevada brushfinch。", "expandable": true, "memberCount": 1, "x": 375.85, "y": -1123.03, "z": -242.65}, {"id": "taxonomy-species-arremon-abeillei", "name": "Black-capped sparrow", "latinName": "Arremon abeillei", "type": "taxonomy", "taxonomyLevel": "species", "summary": "Black-capped sparrow（Arremon abeillei）是图谱中的分类级分类节点，当前关联1种鸟类，如Black-capped sparrow。", "expandable": true, "memberCount": 1, "x": 52.04, "y": -123.39, "z": 709.38}, {"id": "taxonomy-species-arremon-perijanus", "name": "Perijá brushfinch", "latinName": "Arremon perijanus", "type": "taxonomy", "taxonomyLevel": "species", "summary": "Perijá brushfinch（Arremon perijanus）是图谱中的分类级分类节点，当前关联1种鸟类，如Perijá brushfinch。", "expandable": true, "memberCount": 1, "x": -20.51, "y": -617.1, "z": -217.37}, {"id": "taxonomy-species-arremon-taciturnus", "name": "Pectoral sparrow", "latinName": "Arremon taciturnus", "type": "taxonomy", "taxonomyLevel": "species", "summary": "Pectoral sparrow（Arremon taciturnus）是图谱中的分类级分类节点，当前关联1种鸟类，如Pectoral sparrow。", "expandable": true, "memberCount": 1, "x": 1083.54, "y": 244.59, "z": 295.07}, {"id": "taxonomy-species-arremon-brunneinucha", "name": "Chestnut-capped brushfinch", "latinName": "Arremon brunneinucha", "type": "taxonomy", "taxonomyLevel": "species", "summary": "Chestnut-capped brushfinch（Arremon brunneinucha）是图谱中的分类级分类节点，当前关联1种鸟类，如Chestnut-capped brushfinch。", "expandable": true, "memberCount": 1, "x": 167.94, "y": 550.94, "z": -675.22}, {"id": "taxonomy-species-arremon-torquatus", "name": "White-browed brushfinch", "latinName": "Arremon torquatus", "type": "taxonomy", "taxonomyLevel": "species", "summary": "White-browed brushfinch（Arremon torquatus）是图谱中的分类级分类节点，当前关联1种鸟类，如White-browed brushfinch。", "expandable": true, "memberCount": 1, "x": -313.21, "y": -585.5, "z": 279.12}, {"id": "taxonomy-species-arremon-costaricensis", "name": "Costa Rican brushfinch", "latinName": "Arremon costaricensis", "type": "taxonomy", "taxonomyLevel": "species", "summary": "Costa Rican brushfinch（Arremon costaricensis）是图谱中的分类级分类节点，当前关联1种鸟类，如Costa Rican brushfinch。", "expandable": true, "memberCount": 1, "x": -799.69, "y": -490.77, "z": -734.07}, {"id": "taxonomy-species-arremon-nigriceps", "name": "Marañón sparrow", "latinName": "Arremon nigriceps", "type": "taxonomy", "taxonomyLevel": "species", "summary": "Marañón sparrow（Arremon nigriceps）是图谱中的分类级分类节点，当前关联1种鸟类，如Marañón sparrow。", "expandable": true, "memberCount": 1, "x": -552.19, "y": 20.78, "z": -70.27}, {"id": "taxonomy-species-arremon-phygas", "name": "Paria brushfinch", "latinName": "Arremon phygas", "type": "taxonomy", "taxonomyLevel": "species", "summary": "Paria brushfinch（Arremon phygas）是图谱中的分类级分类节点，当前关联1种鸟类，如Paria brushfinch。", "expandable": true, "memberCount": 1, "x": -385.18, "y": 171.51, "z": -71.32}, {"id": "taxonomy-species-arremon-castaneiceps", "name": "Olive finch", "latinName": "Arremon castaneiceps", "type": "taxonomy", "taxonomyLevel": "species", "summary": "Olive finch（Arremon castaneiceps）是图谱中的分类级分类节点，当前关联1种鸟类，如Olive finch。", "expandable": true, "memberCount": 1, "x": 261.63, "y": -348.49, "z": 120.62}, {"id": "taxonomy-species-arremon-semitorquatus", "name": "Half-collared sparrow", "latinName": "Arremon semitorquatus", "type": "taxonomy", "taxonomyLevel": "species", "summary": "Half-collared sparrow（Arremon semitorquatus）是图谱中的分类级分类节点，当前关联1种鸟类，如Half-collared sparrow。", "expandable": true, "memberCount": 1, "x": 174.06, "y": 347.15, "z": -284.17}, {"id": "taxonomy-species-arremon-dorbignii", "name": "Moss-backed sparrow", "latinName": "Arremon dorbignii", "type": "taxonomy", "taxonomyLevel": "species", "summary": "Moss-backed sparrow（Arremon dorbignii）是图谱中的分类级分类节点，当前关联1种鸟类，如Moss-backed sparrow。", "expandable": true, "memberCount": 1, "x": 135.0, "y": 227.13, "z": 362.59}, {"id": "taxonomy-species-arremon-virenticeps", "name": "Green-striped brushfinch", "latinName": "Arremon virenticeps", "type": "taxonomy", "taxonomyLevel": "species", "summary": "Green-striped brushfinch（Arremon virenticeps）是图谱中的分类级分类节点，当前关联1种鸟类，如Green-striped brushfinch。", "expandable": true, "memberCount": 1, "x": -609.74, "y": -510.54, "z": 343.31}, {"id": "taxonomy-species-arremon-phaeopleurus", "name": "Caracas brushfinch", "latinName": "Arremon phaeopleurus", "type": "taxonomy", "taxonomyLevel": "species", "summary": "Caracas brushfinch（Arremon phaeopleurus）是图谱中的分类级分类节点，当前关联1种鸟类，如Caracas brushfinch。", "expandable": true, "memberCount": 1, "x": -61.72, "y": -587.74, "z": 292.76}, {"id": "taxonomy-species-arremon-flavirostris", "name": "Saffron-billed sparrow", "latinName": "Arremon flavirostris", "type": "taxonomy", "taxonomyLevel": "species", "summary": "Saffron-billed sparrow（Arremon flavirostris）是图谱中的分类级分类节点，当前关联1种鸟类，如Saffron-billed sparrow。", "expandable": true, "memberCount": 1, "x": -146.8, "y": -214.3, "z": 594.81}, {"id": "taxonomy-species-arremon-franciscanus", "name": "São Francisco sparrow", "latinName": "Arremon franciscanus", "type": "taxonomy", "taxonomyLevel": "species", "summary": "São Francisco sparrow（Arremon franciscanus）是图谱中的分类级分类节点，当前关联1种鸟类，如São Francisco sparrow。", "expandable": true, "memberCount": 1, "x": 371.36, "y": 322.78, "z": -289.93}, {"id": "taxonomy-species-arremon-schlegeli", "name": "Golden-winged sparrow", "latinName": "Arremon schlegeli", "type": "taxonomy", "taxonomyLevel": "species", "summary": "Golden-winged sparrow（Arremon schlegeli）是图谱中的分类级分类节点，当前关联1种鸟类，如Golden-winged sparrow。", "expandable": true, "memberCount": 1, "x": 2124.3, "y": -999.57, "z": -686.3}], "links": [{"key": "taxonomy-species-arremon-costaricensis__belongs_to_genus__taxonomy-genus-arremon", "source": "taxonomy-species-arremon-costaricensis", "target": "taxonomy-genus-arremon", "relation": "belongs_to_genus", "label": "属于属", "evidence": "依据 birds.csv 分类字段补充：Costa Rican brushfinch 属于属 Arremon。"}, {"key": "taxonomy-species-arremon-basilicus__belongs_to_genus__taxonomy-genus-arremon", "source": "taxonomy-species-arremon-basilicus", "target": "taxonomy-genus-arremon", "relation": "belongs_to_genus", "label": "属于属", "evidence": "依据 birds.csv 分类字段补充：Sierra Nevada brushfinch 属于属 Arremon。"}, {"key": "taxonomy-species-arremon-perijanus__belongs_to_genus__taxonomy-genus-arremon", "source": "taxonomy-species-arremon-perijanus", "target": "taxonomy-genus-arremon", "relation": "belongs_to_genus", "label": "属于属", "evidence": "依据 birds.csv 分类字段补充：Perijá brushfinch 属于属 Arremon。"}, {"key": "taxonomy-species-arremon-atricapillus__belongs_to_genus__taxonomy-genus-arremon", "source": "taxonomy-species-arremon-atricapillus", "target": "taxonomy-genus-arremon", "relation": "belongs_to_genus", "label": "属于属", "evidence": "依据 birds.csv 分类字段补充：Black-headed brushfinch 属于属 Arremon。"}, {"key": "taxonomy-species-arremon-phaeopleurus__belongs_to_genus__taxonomy-genus-arremon", "source": "taxonomy-species-arremon-phaeopleurus", "target": "taxonomy-genus-arremon", "relation": "belongs_to_genus", "label": "属于属", "evidence": "依据 birds.csv 分类字段补充：Caracas brushfinch 属于属 Arremon。"}, {"key": "taxonomy-species-arremon-phygas__belongs_to_genus__taxonomy-genus-arremon", "source": "taxonomy-species-arremon-phygas", "target": "taxonomy-genus-arremon", "relation": "belongs_to_genus", "label": "属于属", "evidence": "依据 birds.csv 分类字段补充：Paria brushfinch 属于属 Arremon。"}, {"key": "taxonomy-species-arremon-assimilis__belongs_to_genus__taxonomy-genus-arremon", "source": "taxonomy-species-arremon-assimilis", "target": "taxonomy-genus-arremon", "relation": "belongs_to_genus", "label": "属于属", "evidence": "依据 birds.csv 分类字段补充：Grey-browed brushfinch 属于属 Arremon。"}, {"key": "taxonomy-species-arremon-torquatus__belongs_to_genus__taxonomy-genus-arremon", "source": "taxonomy-species-arremon-torquatus", "target": "taxonomy-genus-arremon", "relation": "belongs_to_genus", "label": "属于属", "evidence": "依据 birds.csv 分类字段补充：White-browed brushfinch 属于属 Arremon。"}, {"key": "taxonomy-species-arremon-aurantiirostris__belongs_to_genus__taxonomy-genus-arremon", "source": "taxonomy-species-arremon-aurantiirostris", "target": "taxonomy-genus-arremon", "relation": "belongs_to_genus", "label": "属于属", "evidence": "依据 birds.csv 分类字段补充：Orange-billed sparrow 属于属 Arremon。"}, {"key": "taxonomy-species-arremon-abeillei__belongs_to_genus__taxonomy-genus-arremon", "source": "taxonomy-species-arremon-abeillei", "target": "taxonomy-genus-arremon", "relation": "belongs_to_genus", "label": "属于属", "evidence": "依据 birds.csv 分类字段补充：Black-capped sparrow 属于属 Arremon。"}, {"key": "taxonomy-species-arremon-nigriceps__belongs_to_genus__taxonomy-genus-arremon", "source": "taxonomy-species-arremon-nigriceps", "target": "taxonomy-genus-arremon", "relation": "belongs_to_genus", "label": "属于属", "evidence": "依据 birds.csv 分类字段补充：Marañón sparrow 属于属 Arremon。"}, {"key": "taxonomy-species-arremon-schlegeli__belongs_to_genus__taxonomy-genus-arremon", "source": "taxonomy-species-arremon-schlegeli", "target": "taxonomy-genus-arremon", "relation": "belongs_to_genus", "label": "属于属", "evidence": "依据 birds.csv 分类字段补充：Golden-winged sparrow 属于属 Arremon。"}, {"key": "taxonomy-species-arremon-taciturnus__belongs_to_genus__taxonomy-genus-arremon", "source": "taxonomy-species-arremon-taciturnus", "target": "taxonomy-genus-arremon", "relation": "belongs_to_genus", "label": "属于属", "evidence": "依据 birds.csv 分类字段补充：Pectoral sparrow 属于属 Arremon。"}, {"key": "taxonomy-species-arremon-axillaris__belongs_to_genus__taxonomy-genus-arremon", "source": "taxonomy-species-arremon-axillaris", "target": "taxonomy-genus-arremon", "relation": "belongs_to_genus", "label": "属于属", "evidence": "依据 birds.csv 分类字段补充：Yellow-mandibled sparrow 属于属 Arremon。"}, {"key": "taxonomy-species-arremon-franciscanus__belongs_to_genus__taxonomy-genus-arremon", "source": "taxonomy-species-arremon-franciscanus", "target": "taxonomy-genus-arremon", "relation": "belongs_to_genus", "label": "属于属", "evidence": "依据 birds.csv 分类字段补充：São Francisco sparrow 属于属 Arremon。"}, {"key": "taxonomy-species-arremon-semitorquatus__belongs_to_genus__taxonomy-genus-arremon", "source": "taxonomy-species-arremon-semitorquatus", "target": "taxonomy-genus-arremon", "relation": "belongs_to_genus", "label": "属于属", "evidence": "依据 birds.csv 分类字段补充：Half-collared sparrow 属于属 Arremon。"}, {"key": "taxonomy-species-arremon-dorbignii__belongs_to_genus__taxonomy-genus-arremon", "source": "taxonomy-species-arremon-dorbignii", "target": "taxonomy-genus-arremon", "relation": "belongs_to_genus", "label": "属于属", "evidence": "依据 birds.csv 分类字段补充：Moss-backed sparrow 属于属 Arremon。"}, {"key": "taxonomy-species-arremon-flavirostris__belongs_to_genus__taxonomy-genus-arremon", "source": "taxonomy-species-arremon-flavirostris", "target": "taxonomy-genus-arremon", "relation": "belongs_to_genus", "label": "属于属", "evidence": "依据 birds.csv 分类字段补充：Saffron-billed sparrow 属于属 Arremon。"}, {"key": "taxonomy-species-arremon-virenticeps__belongs_to_genus__taxonomy-genus-arremon", "source": "taxonomy-species-arremon-virenticeps", "target": "taxonomy-genus-arremon", "relation": "belongs_to_genus", "label": "属于属", "evidence": "依据 birds.csv 分类字段补充：Green-striped brushfinch 属于属 Arremon。"}, {"key": "taxonomy-species-arremon-brunneinucha__belongs_to_genus__taxonomy-genus-arremon", "source": "taxonomy-species-arremon-brunneinucha", "target": "taxonomy-genus-arremon", "relation": "belongs_to_genus", "label": "属于属", "evidence": "依据 birds.csv 分类字段补充：Chestnut-capped brushfinch 属于属 Arremon。"}, {"key": "taxonomy-species-arremon-crassirostris__belongs_to_genus__taxonomy-genus-arremon", "source": "taxonomy-species-arremon-crassirostris", "target": "taxonomy-genus-arremon", "relation": "belongs_to_genus", "label": "属于属", "evidence": "依据 birds.csv 分类字段补充：Sooty-faced finch 属于属 Arremon。"}, {"key": "taxonomy-species-arremon-castaneiceps__belongs_to_genus__taxonomy-genus-arremon", "source": "taxonomy-species-arremon-castaneiceps", "target": "taxonomy-genus-arremon", "relation": "belongs_to_genus", "label": "属于属", "evidence": "依据 birds.csv 分类字段补充：Olive finch 属于属 Arremon。"}]}