{
  "fetched_at": "2026-05-21T19:27:56",
  "en": {
    "requested_title": "Short-billed Canastero",
    "resolved_title": "Short-billed canastero",
    "url": "https://en.wikipedia.org/wiki/Short-billed_canastero",
    "page_id": 12436250,
    "extract": "The short-billed canastero (Asthenes baeri) is a species of bird in the Furnariinae subfamily of the ovenbird family Furnariidae. It is found in Argentina, Bolivia, Brazil, Paraguay, and Uruguay.\n\n\nTaxonomy and systematics\nThe short-billed canastero's taxonomy is unsettled. The International Ornithological Committee (IOC) and BirdLife International's Handbook of the Birds of the World (HBW) assign it three subspecies, the nominate A. b. baeri (Berlepsch, 1906), A. b. chacoensis (Brodkorb, 1938), and \nA. b. neiffi (Contreras, 1980). The Clements taxonomy does not recognize neiffi, assessing it as a clinal variant of chacoensis.\nThis article follows the three-subspecies model.\n\n\nDescription\nThe short-billed canastero is 14 to 15 cm (5.5 to 5.9 in) long and weighs 10 to 18 g (0.35 to 0.63 oz). It has a short and thick bill, and is more similar to the wholly unrelated little thornbird (Phacellodomus sibilatrix) than to other canasteros. The sexes have the same plumage. Adults of the nominate subspecies have an indistinct wide grayish supercilium on an otherwise dull grayish brown face. Their crown is dull gray-brown, their back a slightly grayer brown, and their rump and uppertail coverts gray with a brown tinge. Their wings are mostly dull grayish brown with paler gray edges on the coverts and flight feathers. Their tail's innermost two pairs of feathers are mostly dark brownish fuscous and the rest mostly dull rufous. Their chin is pale grayish, their upper throat orange-tawny with a darker lower margin, and their lower throat, breast, and belly pale dull grayish. Their flanks and undertail coverts are pale rufescent. Their iris is brown to grayish brown, their maxilla black to dark gray or dark brown, their mandible gray to pinkish gray, and their legs and feet gray to brownish gray. Juveniles have little or no orange-tawny on the throat and a mottled upper breast. Subspecies A. b. chacoensis is very slightly paler than the nominate and has a whiter supercilium and more rufous on the tail. A. b. neiffi is described as significantly larger than the other two subspecies but differs little in plumage from chacoensis.\n\n\nDistribution and habitat\nThe nominate subspecies of the short-billed canastero is found in southern Bolivia, western Paraguay, central Argentina, extreme southeastern Brazil, and western Uruguay. Subspecies A. b. chacoensis is found in extreme south-central Bolivia and northwestern Paraguay. A. b. neiffi is found in western Argentina. The species inhabits arid lowland scrublands, Gran Chaco scrub and woodlands, and woodlands of the Monte Desert. In elevation it ranges from sea level to 1,300 m (4,300 ft).\n\n\nBehavior\n\n\nMovement\nThe short-billed canastero is a year-round resident throughout its range.\n\n\nFeeding\nThe short-billed canastero feeds on a wide variety of arthropods. It forages singly or in pairs, apparently capturing prey by gleaning low vegetation and to a lesser extent on the ground.\n\n\nBreeding\nThe short-billed canastero breeds in the austral spring and summer, including at least October to January. It is thought to be monogamous. It builds an oval nest of spiny branches up to 35 cm (14 in) wide and 20 cm (8 in) tall, placed 1 to 3 m (3 to 10 ft) high in the fork of a tree or bush. Its entrance is on the top and a tunnel leads to the nest chamber, which is floored with feathers, hair, flowers, moss, and other soft material. The clutch size is usually three eggs but can be as many as five. The incubation period is 14 to 15.5 days and fledging occurs about 14 days after hatch.\n\n\nVocalization\nThe short-billed canastero's song is \"a high-pitched, fast seep seep seepseepseep..., speeding up to and ending in a trill\". Sometimes the introductory notes are omitted. It also gives a \"series of short, buzzing 'pzzz' phrases.\n\n\nStatus\nThe IUCN has assessed the short-billed canastero as being of Least Concern. It has a very large range but an unknown population size that is believed to be decreasing. No immediate threats have been identified. It is considered uncommon to fairly common and occurs in several protected areas. \"Habitat occupied by this species is subject to at least moderate disturbance and grazing in large parts of its range.\"\n\n\nReferences",
    "wikitext": "{{Short description|Species of bird}}\n{{Use American English|date=September 2023}}\n\n{{Speciesbox\n| name = Short-billed canastero\n| image = Asthenes baeri - Short-billed canastero.jpg\n| status = LC\n| status_system = IUCN3.1\n| status_ref = <ref name=IUCN>{{cite iucn |author=BirdLife International |date=2016 |title=Short-billed Canastero ''Asthenes baeri'' |volume=2016 |article-number=e.T22702491A93877497 |doi=10.2305/IUCN.UK.2016-3.RLTS.T22702491A93877497.en |access-date=23 September 2023}}</ref>\n| genus = Asthenes\n| species = baeri\n| authority = ([[Hans von Berlepsch|Berlepsch]], 1906)\n| subdivision_ranks = Subspecies\n| subdivision = See text\n| synonyms =\n| range_map = Asthenes baeri map.svg\n}}\n\nThe '''short-billed canastero''' ('''''Asthenes baeri''''') is a species of [[bird]] in the Furnariinae subfamily of the ovenbird [[Family (taxonomy)|family]] [[Furnariidae]]. It is found in [[Argentina]], [[Bolivia]], [[Brazil]], [[Paraguay]], and [[Uruguay]].<ref name=IOC13.2>{{cite web |url=https://www.worldbirdnames.org/new/bow/ovenbirds/ |title=Ovenbirds, woodcreepers |website=IOC World Bird List |version =v 13.2 | editor1-last=Gill | editor1-first=Frank | editor1-link=Frank Gill (ornithologist) | editor2-last=Donsker | editor2-first=David | editor3-last=Rasmussen | editor3-first=Pamela | editor3-link=Pamela Rasmussen |date=July 2023 |access-date=July 31, 2023 }}</ref>\n\n==Taxonomy and systematics==\n\nThe short-billed canastero's taxonomy is unsettled. The [[International Ornithological Committee]] (IOC) and [[BirdLife International]]'s ''[[Handbook of the Birds of the World]]'' (HBW) assign it three subspecies, the [[Nominate subspecies|nominate]] ''A. b. baeri'' ([[Hans von Berlepsch|Berlepsch]], 1906), ''A. b. chacoensis'' ([[Pierce Brodkorb|Brodkorb]], 1938), and \n''A. b. neiffi'' ([[Julio R. Contreras Roqué|Contreras]], 1980).<ref name=IOC13.2/><ref name=HBW7>HBW and BirdLife International (2022) Handbook of the Birds of the World and BirdLife International digital checklist of the birds of the world. Version 7. Available at: https://datazone.birdlife.org/userfiles/file/Species/Taxonomy/HBW-BirdLife_Checklist_v7_Dec22.zip retrieved December 13, 2022</ref> The [[Clements taxonomy]] does not recognize ''neiffi'', assessing it as a [[Cline (biology)|clinal]] variant of ''chacoensis''.<ref name=Clements2022>Clements, J. F., T. S. Schulenberg, M. J. Iliff, T. A. Fredericks, J. A. Gerbracht, D. Lepage, S. M. Billerman, B. L. Sullivan, and C. L. Wood. 2022. The eBird/Clements checklist of birds of the world: v2022. Downloaded from https://www.birds.cornell.edu/clementschecklist/download/ retrieved November 10, 2022</ref>\n\nThis article follows the three-subspecies model.\n\n==Description==\n\nThe short-billed canastero is {{convert|14|to|15|cm|in|sigfig=2|abbr=on}} long and weighs {{convert|10|to|18|g|oz|sigfig=2|abbr=on}}. It has a short and thick bill, and is more similar to the wholly unrelated [[little thornbird]] (''Phacellodomus sibilatrix'') than to other canasteros. The sexes have the same plumage. Adults of the nominate subspecies have an indistinct wide grayish [[supercilium]] on an otherwise dull grayish brown face. Their crown is dull gray-brown, their back a slightly grayer brown, and their rump and uppertail [[Covert feather|coverts]] gray with a brown tinge. Their wings are mostly dull grayish brown with paler gray edges on the coverts and flight feathers. Their tail's innermost two pairs of feathers are mostly dark brownish [[fuscous]] and the rest mostly dull rufous. Their chin is pale grayish, their upper throat orange-tawny with a darker lower margin, and their lower throat, breast, and belly pale dull grayish. Their flanks and undertail coverts are pale rufescent. Their iris is brown to grayish brown, their [[maxilla]] black to dark gray or dark brown, their [[mandible]] gray to pinkish gray, and their legs and feet gray to brownish gray. Juveniles have little or no orange-tawny on the throat and a mottled upper breast. Subspecies ''A. b. chacoensis'' is very slightly paler than the nominate and has a whiter supercilium and more rufous on the tail. ''A. b. neiffi'' is described as significantly larger than the other two subspecies but differs little in plumage from ''chacoensis''.<ref name=SBCA-BOW>Remsen, Jr., J. V. (2020). Short-billed Canastero (''Asthenes baeri''), version 1.0. In Birds of the World (J. del Hoyo, A. Elliott, J. Sargatal, D. A. Christie, and E. de Juana, Editors). Cornell Lab of Ornithology, Ithaca, NY, USA. https://doi.org/10.2173/bow.shbcan1.01 retrieved September 23, 2023</ref><ref name=vanPerlo>{{cite book | last =van Perlo | first = Ber| title =A Field Guide to the Birds of Brazil | publisher =Oxford University Press | date =2009 | location =New York | page =208 | isbn =978-0-19-530155-7 }}</ref><ref name=Peña>{{cite book | last =de la Peña | first =Martín R. | last2=Rumboll |first2=Maurice|  title =Birds of Southern South America and Antarctica | publisher =Princeton University Press | series =Princeton Illustrated Checklists | date =2001 | location =New Jersey | pages =Plate 63 | isbn =0-691-09035-1 }}</ref>\n\n==Distribution and habitat==\n\nThe nominate subspecies of the short-billed canastero is found in southern Bolivia, western Paraguay, central Argentina, extreme southeastern Brazil, and western Uruguay. Subspecies ''A. b. chacoensis'' is found in extreme south-central Bolivia and northwestern Paraguay.<ref name=SBCA-BOW/><ref name=IOC13.2/> ''A. b. neiffi'' is found in western Argentina.<ref name=IOC13.2/> The species inhabits arid lowland scrublands, [[Gran Chaco]] scrub and woodlands, and woodlands of the [[Monte Desert]]. In elevation it ranges from sea level to {{convert|1300|m|ft|abbr=on}}.<ref name=SBCA-BOW/><ref name=vanPerlo/><ref name=Peña/>\n\n==Behavior==\n===Movement===\n\nThe short-billed canastero is a year-round resident throughout its range.<ref name=SBCA-BOW/>\n\n===Feeding===\n\nThe short-billed canastero feeds on a wide variety of [[arthropod]]s. It forages singly or in pairs, apparently capturing prey by gleaning low vegetation and to a lesser extent on the ground.<ref name=SBCA-BOW/>\n\n===Breeding===\n\nThe short-billed canastero breeds in the [[South|austral]] spring and summer, including at least October to January. It is thought to be monogamous. It builds an oval nest of spiny branches up to {{convert|35|cm|in|abbr=on}} wide and {{convert|20|cm|in|0|abbr=on}} tall, placed {{convert|1|to|3|m|ft|sigfig=1|abbr=on}} high in the fork of a tree or bush. Its entrance is on the top and a tunnel leads to the nest chamber, which is floored with feathers, hair, flowers, moss, and other soft material. The clutch size is usually three eggs but can be as many as five. The incubation period is 14 to 15.5 days and fledging occurs about 14 days after hatch.<ref name=SBCA-BOW/>\n\n{{birdsong|url=https://xeno-canto.org/species/Asthenes-baeri |species=short-billed casastero}}\n\n===Vocalization===\n\nThe short-billed canastero's song is \"a high-pitched, fast ''seep seep seepseepseep...'', speeding up to and ending in a trill\".<ref name=Peña/> Sometimes the introductory notes are omitted. It also gives a \"series of short, buzzing 'pzzz' phrases.<ref name=SBCA-BOW/>\n\n==Status==\n\nThe [[IUCN]] has assessed the short-billed canastero as being of Least Concern. It has a very large range but an unknown population size that is believed to be decreasing. No immediate threats have been identified.<ref name=IUCN/> It is considered uncommon to fairly common and occurs in several protected areas. \"Habitat occupied by this species is subject to at least moderate disturbance and grazing in large parts of its range.\"<ref name=SBCA-BOW/>\n\n==References==\n{{Reflist}}\n\n{{Taxonbar|from=Q1266461}}\n\n[[Category:Asthenes|short-billed canastero]]\n[[Category:Birds of Argentina]]\n[[Category:Birds of Paraguay]]\n[[Category:Birds of Uruguay]]\n[[Category:Birds described in 1906|short-billed canastero]]\n[[Category:Taxa named by Hans von Berlepsch|short-billed canastero]]\n[[Category:Taxonomy articles created by Polbot]]",
    "coordinates": {
      "lat": null,
      "lng": null
    },
    "zh_title": "",
    "image_url": "https://upload.wikimedia.org/wikipedia/commons/thumb/7/74/Asthenes_baeri_-_Short-billed_canastero.jpg/960px-Asthenes_baeri_-_Short-billed_canastero.jpg"
  },
  "zh": null,
  "parsed": {
    "status": "LC",
    "taxon_name": ""
  }
}